surround_to_eac3/__init__.py
surround_to_eac3/gui.py
surround_to_eac3/main.py
surround_to_eac3/processing.py
surround_to_eac3-0.5.1.dist-info/licenses/LICENSE
surround_to_eac3-0.5.1.dist-info/METADATA
surround_to_eac3-0.5.1.dist-info/WHEEL
surround_to_eac3-0.5.1.dist-info/entry_points.txt
surround_to_eac3-0.5.1.dist-info/top_level.txt
surround_to_eac3-0.5.1.dist-info/RECORD
