Metadata-Version: 2.4
Name: surround-to-eac3
Version: 0.5.1
Summary: A CLI tool to transcode 5.1 audio in video files to E-AC3.
Home-page: https://github.com/jono-rams/surround-to-eac3
Author: Jonathan Rampersad
Author-email: jonathan@jono-rams.work
Classifier: Development Status :: 4 - Beta
Classifier: Intended Audience :: End Users/Desktop
Classifier: Programming Language :: Python :: 3
Classifier: Programming Language :: Python :: 3.10
Classifier: Programming Language :: Python :: 3.11
Classifier: Programming Language :: Python :: 3.12
Classifier: License :: OSI Approved :: MIT License
Classifier: Operating System :: OS Independent
Classifier: Topic :: Multimedia :: Sound/Audio :: Conversion
Requires-Python: >=3.10
License-File: LICENSE
Requires-Dist: tqdm
Requires-Dist: platformdirs
Requires-Dist: customtkinter>=5.0.0
Dynamic: license-file
